README.md
setup.cfg
setup.py
slugify.py
slugify_python.egg-info/PKG-INFO
slugify_python.egg-info/SOURCES.txt
slugify_python.egg-info/dependency_links.txt
slugify_python.egg-info/top_level.txt