Metadata-Version: 2.1
Name: slugify-python
Version: 1.0.0
Summary: Python slugify library
Author: Hassan Sammour
